Workbook
Name Slicer_Month: #N/A

Sheet Data
A1: Month | B1: Column1 | C1: Category | D1: Budget | E1: Actual | F1: Variance ₹ | G1: Variance % | H1: Type | I1: Result
A2: January | B2: 1 | C2: Revenue | D2: 1000000 | E2: 950000 | F2: =Table2[[#This Row],[Actual]]-Table2[[#This Row],[Budget]] -> -50000 | G2: =Table2[[#This Row],[Variance ₹]]/Table2[[#This Row],[Budget]] -> -0.05 | H2: Revenue | I2: =IF($H2="Revenue",IF($E2>=$D2,"Favorable","Unfavorable"),IF($E2<=$D2,"Favorable","Unfavorable")) -> Unfavorable
A3: January | B3: 1 | C3: Salary | D3: 300000 | E3: 320000 | F3: =Table2[[#This Row],[Actual]]-Table2[[#This Row],[Budget]] -> 20000 | G3: =Table2[[#This Row],[Variance ₹]]/Table2[[#This Row],[Budget]] -> 0.066666667 | H3: Cost | I3: =IF($H3="Revenue",IF($E3>=$D3,"Favorable","Unfavorable"),IF($E3<=$D3,"Favorable","Unfavorable")) -> Unfavorable
A4: January | B4: 1 | C4: Marketing | D4: 80000 | E4: 70000 | F4: =Table2[[#This Row],[Actual]]-Table2[[#This Row],[Budget]] -> -10000 | G4: =Table2[[#This Row],[Variance ₹]]/Table2[[#This Row],[Budget]] -> -0.125 | H4: Cost | I4: =IF($H4="Revenue",IF($E4>=$D4,"Favorable","Unfavorable"),IF($E4<=$D4,"Favorable","Unfavorable")) -> Favorable
A5: January | B5: 1 | C5: IT Expense | D5: 50000 | E5: 55000 | F5: =Table2[[#This Row],[Actual]]-Table2[[#This Row],[Budget]] -> 5000 | G5: =Table2[[#This Row],[Variance ₹]]/Table2[[#This Row],[Budget]] -> 0.1 | H5: Cost | I5: =IF($H5="Revenue",IF($E5>=$D5,"Favorable","Unfavorable"),IF($E5<=$D5,"Favorable","Unfavorable")) -> Unfavorable
A6: January | B6: 1 | C6: Admin Expense | D6: 40000 | E6: 42000 | F6: =Table2[[#This Row],[Actual]]-Table2[[#This Row],[Budget]] -> 2000 | G6: =Table2[[#This Row],[Variance ₹]]/Table2[[#This Row],[Budget]] -> 0.05 | H6: Cost | I6: =IF($H6="Revenue",IF($E6>=$D6,"Favorable","Unfavorable"),IF($E6<=$D6,"Favorable","Unfavorable")) -> Unfavorable
A7: February | B7: 2 | C7: Revenue | D7: 1050000 | E7: 1020000 | F7: =Table2[[#This Row],[Actual]]-Table2[[#This Row],[Budget]] -> -30000 | G7: =Table2[[#This Row],[Variance ₹]]/Table2[[#This Row],[Budget]] -> -0.028571429 | H7: Revenue | I7: =IF($H7="Revenue",IF($E7>=$D7,"Favorable","Unfavorable"),IF($E7<=$D7,"Favorable","Unfavorable")) -> Unfavorable
A8: February | B8: 2 | C8: Salary | D8: 300000 | E8: 300000 | F8: =Table2[[#This Row],[Actual]]-Table2[[#This Row],[Budget]] -> 0 | G8: =Table2[[#This Row],[Variance ₹]]/Table2[[#This Row],[Budget]] -> 0 | H8: Cost | I8: =IF($H8="Revenue",IF($E8>=$D8,"Favorable","Unfavorable"),IF($E8<=$D8,"Favorable","Unfavorable")) -> Favorable
A9: February | B9: 2 | C9: Marketing | D9: 85000 | E9: 88000 | F9: =Table2[[#This Row],[Actual]]-Table2[[#This Row],[Budget]] -> 3000 | G9: =Table2[[#This Row],[Variance ₹]]/Table2[[#This Row],[Budget]] -> 0.035294118 | H9: Cost | I9: =IF($H9="Revenue",IF($E9>=$D9,"Favorable","Unfavorable"),IF($E9<=$D9,"Favorable","Unfavorable")) -> Unfavorable
A10: February | B10: 2 | C10: IT Expense | D10: 50000 | E10: 48000 | F10: =Table2[[#This Row],[Actual]]-Table2[[#This Row],[Budget]] -> -2000 | G10: =Table2[[#This Row],[Variance ₹]]/Table2[[#This Row],[Budget]] -> -0.04 | H10: Cost | I10: =IF($H10="Revenue",IF($E10>=$D10,"Favorable","Unfavorable"),IF($E10<=$D10,"Favorable","Unfavorable")) -> Favorable
A11: February | B11: 2 | C11: Admin Expense | D11: 42000 | E11: 43000 | F11: =Table2[[#This Row],[Actual]]-Table2[[#This Row],[Budget]] -> 1000 | G11: =Table2[[#This Row],[Variance ₹]]/Table2[[#This Row],[Budget]] -> 0.023809524 | H11: Cost | I11: =IF($H11="Revenue",IF($E11>=$D11,"Favorable","Unfavorable"),IF($E11<=$D11,"Favorable","Unfavorable")) -> Unfavorable
A12: March | B12: 3 | C12: Revenue | D12: 1100000 | E12: 1130000 | F12: =Table2[[#This Row],[Actual]]-Table2[[#This Row],[Budget]] -> 30000 | G12: =Table2[[#This Row],[Variance ₹]]/Table2[[#This Row],[Budget]] -> 0.027272727 | H12: Revenue | I12: =IF($H12="Revenue",IF($E12>=$D12,"Favorable","Unfavorable"),IF($E12<=$D12,"Favorable","Unfavorable")) -> Favorable
A13: March | B13: 3 | C13: Salary | D13: 305000 | E13: 308000 | F13: =Table2[[#This Row],[Actual]]-Table2[[#This Row],[Budget]] -> 3000 | G13: =Table2[[#This Row],[Variance ₹]]/Table2[[#This Row],[Budget]] -> 0.0098360656 | H13: Cost | I13: =IF($H13="Revenue",IF($E13>=$D13,"Favorable","Unfavorable"),IF($E13<=$D13,"Favorable","Unfavorable")) -> Unfavorable
... A61: December | B61: 12 | C61: Admin Expense | D61: 48000 | E61: 50000 | F61: =Table2[[#This Row],[Actual]]-Table2[[#This Row],[Budget]] -> 2000 | G61: =Table2[[#This Row],[Variance ₹]]/Table2[[#This Row],[Budget]] -> 0.041666667 | H61: Cost | I61: =IF($H61="Revenue",IF($E61>=$D61,"Favorable","Unfavorable"),IF($E61<=$D61,"Favorable","Unfavorable")) -> Unfavorable

Sheet FP&A Summary
A2: Total Revenue Variance | B2: =SUMIFS(Table2[Variance ₹],Table2[Type],"Revenue") -> -120000
A3: Total Cost Variance | B3: =SUMIFS(Table2[Variance ₹],Table2[Type],"Cost") -> 91000
A4: Net P&L Impact | B4: =B2-B3 -> -211000
A6: No. of Favorable Items | B6: =COUNTIF(Table2[Result],"Favorable") -> 18
A7: No. of Unfavorable Items | B7: =COUNTIF(Table2[Result],"Unfavorable") -> 42
A10: Category | B10: Budget | C10: Actual | D10: Variance ₹ | E10: Variance % | F10: Result
A11: Revenue | B11: =SUMIFS(Table2[Budget],Table2[Category],"Revenue") -> 15300000 | C11: =SUMIFS(Table2[Actual],Table2[Category],"Revenue") -> 15180000 | D11: =Table35[[#This Row],[Actual]]-Table35[[#This Row],[Budget]] -> -120000 | E11: =Table35[[#This Row],[Variance ₹]]/Table35[[#This Row],[Budget]] -> -0.0078431373 | F11: =IF(Table35[[#This Row],[Category]]="Revenue",IF(Table35[[#This Row],[Variance ₹]]>=0,"Favorable","Unfavorable"),IF(Table35[[#This Row],[Variance ₹]]<=0,"Favorable","Unfavorable")) -> Unfavorable
A12: Salary | B12: =SUMIFS(Table2[Budget],Table2[Category],"Salary") -> 3750000 | C12: =SUMIFS(Table2[Actual],Table2[Category],"Salary") -> 3794000 | D12: =Table35[[#This Row],[Actual]]-Table35[[#This Row],[Budget]] -> 44000 | E12: =Table35[[#This Row],[Variance ₹]]/Table35[[#This Row],[Budget]] -> 0.011733333 | F12: =IF(Table35[[#This Row],[Category]]="Revenue",IF(Table35[[#This Row],[Variance ₹]]>=0,"Favorable","Unfavorable"),IF(Table35[[#This Row],[Variance ₹]]<=0,"Favorable","Unfavorable")) -> Unfavorable
A13: Marketing | B13: =SUMIFS(Table2[Budget],Table2[Category],"Marketing") -> 1270000 | C13: =SUMIFS(Table2[Actual],Table2[Category],"Marketing") -> 1288000 | D13: =Table35[[#This Row],[Actual]]-Table35[[#This Row],[Budget]] -> 18000 | E13: =Table35[[#This Row],[Variance ₹]]/Table35[[#This Row],[Budget]] -> 0.014173228 | F13: =IF(Table35[[#This Row],[Category]]="Revenue",IF(Table35[[#This Row],[Variance ₹]]>=0,"Favorable","Unfavorable"),IF(Table35[[#This Row],[Variance ₹]]<=0,"Favorable","Unfavorable")) -> Unfavorable
A14: IT Expense | B14: =SUMIFS(Table2[Budget],Table2[Category],"IT Expense") -> 643000 | C14: =SUMIFS(Table2[Actual],Table2[Category],"IT Expense") -> 658000 | D14: =Table35[[#This Row],[Actual]]-Table35[[#This Row],[Budget]] -> 15000 | E14: =Table35[[#This Row],[Variance ₹]]/Table35[[#This Row],[Budget]] -> 0.023328149 | F14: =IF(Table35[[#This Row],[Category]]="Revenue",IF(Table35[[#This Row],[Variance ₹]]>=0,"Favorable","Unfavorable"),IF(Table35[[#This Row],[Variance ₹]]<=0,"Favorable","Unfavorable")) -> Unfavorable
A15: Admin Expense | B15: =SUMIFS(Table2[Budget],Table2[Category],"Admin Expense") -> 531000 | C15: =SUMIFS(Table2[Actual],Table2[Category],"Admin Expense") -> 545000 | D15: =Table35[[#This Row],[Actual]]-Table35[[#This Row],[Budget]] -> 14000 | E15: =Table35[[#This Row],[Variance ₹]]/Table35[[#This Row],[Budget]] -> 0.026365348 | F15: =IF(Table35[[#This Row],[Category]]="Revenue",IF(Table35[[#This Row],[Variance ₹]]>=0,"Favorable","Unfavorable"),IF(Table35[[#This Row],[Variance ₹]]<=0,"Favorable","Unfavorable")) -> Unfavorable

Sheet Pivot_category driver summary
A3: Row Labels | B3: Sum of Budget | C3: Sum of Actual
A4: Revenue | B4: 15300000 | C4: 15180000
A5: Salary | B5: 3750000 | C5: 3794000
A6: Marketing | B6: 1270000 | C6: 1288000
A7: IT Expense | B7: 643000 | C7: 658000
A8: Admin Expense | B8: 531000 | C8: 545000
A9: Grand Total | B9: 21494000 | C9: 21465000
A12: Row Labels | B12: Sum of Variance ₹
A13: Revenue | B13: -120000
A14: Salary | B14: 44000
A15: Marketing | B15: 18000
A16: IT Expense | B16: 15000
A17: Admin Expense | B17: 14000
A18: Grand Total | B18: -29000

Sheet Pivot_Month_Trend
A3: Sum of Variance ₹ | B3: Column Labels
A4: Row Labels | B4: Cost | C4: Revenue | D4: Grand Total
A5: January | B5: 17000 | C5: -50000 | D5: -33000
A6: February | B6: 2000 | C6: -30000 | D6: -28000
A7: March | B7: 9000 | C7: 30000 | D7: 39000
A8: April | B8: 7000 | C8: -40000 | D8: -33000
A9: May | B9: 6000 | C9: 40000 | D9: 46000
A10: June | B10: 12000 | C10: -40000 | D10: -28000
A11: July | B11: 1000 | C11: -20000 | D11: -19000
A12: August | B12: 5000 | C12: 20000 | D12: 25000
A13: September | B13: 9000 | C13: -40000 | D13: -31000
A14: October | B14: 3000 | C14: 30000 | D14: 33000
A15: November | B15: 9000 | C15: 20000 | D15: 29000
A16: December | B16: 11000 | C16: -40000 | D16: -29000
A17: Grand Total | B17: 91000 | C17: -120000 | D17: -29000

Sheet Pivot_KPI Summary
A3: Count of Result | B3: Column Labels
A4: Row Labels | B4: Favorable | C4: Unfavorable | D4: Grand Total
A5: Revenue | B5: 5 | C5: 7 | D5: 12
A6: Salary | B6: 3 | C6: 9 | D6: 12
A7: Marketing | B7: 4 | C7: 8 | D7: 12
A8: IT Expense | B8: 4 | C8: 8 | D8: 12
A9: Admin Expense | B9: 2 | C9: 10 | D9: 12
A10: Grand Total | B10: 18 | C10: 42 | D10: 60

Sheet Dashboard
A2: Net P&L Impact | B2: ='FP&A Summary'!B4 -> -211000
A3: Total Revenue Variance | B3: ='FP&A Summary'!B2 -> -120000
A4: Total Cost Variance | B4: ='FP&A Summary'!B3 -> 91000
A5: Favorable Items | B5: ='FP&A Summary'!B6 -> 18
A6: Unfavorable Items | B6: ='FP&A Summary'!B7 -> 42
A7: Variance % Overall | B7: =B2/(SUM(Table2[Budget])) -> -0.009816693
A8: Biggest Problem Category | B8: =INDEX(Table2[Category],MATCH(MIN(Table2[Variance %]),Table2[Variance %],0)) -> Marketing
A45: Key Insights
A47: • Revenue shortfall of ₹1.20L is main driver of negative P&L
A48: • Salary overspend ₹44K is largest cost variance
A49: • Marketing shows mixed performance
A50: • 70% items are Unfavorable → cost control needed
